mpl_playback/__init__.py
mpl_playback/_schema_vesion.py
mpl_playback/_version.py
mpl_playback/playback.py
mpl_playback/record.py
mpl_playback/scraper.py
mpl_playback/util.py
mpl_playback-0.4.0.dist-info/LICENSE
mpl_playback-0.4.0.dist-info/METADATA
mpl_playback-0.4.0.dist-info/WHEEL
mpl_playback-0.4.0.dist-info/top_level.txt
mpl_playback-0.4.0.dist-info/RECORD
