Metadata-Version: 2.1
Name: mpl-playback
Version: 0.4.0
Summary: Record and playback matplotlib figures
Home-page: https://github.com/ianhi/mpl-playback
Download-URL: https://github.com/ianhi/mpl-playback
Author: Ian Hunt-Isaak
Author-email: ianhuntisaak@gmail.com
License: BSD-3-Clause
Project-URL: Source, https://github.com/ianhi/mpl-playback
Project-URL: Tracker, https://github.com/ianhi/mpl-playback/issues
Keywords: matplotlib,gif
Classifier: Framework :: Matplotlib
Classifier: Intended Audience :: Developers
Classifier: Intended Audience :: Science/Research
Classifier: License :: OSI Approved :: BSD License
Classifier: Operating System :: OS Independent
Classifier: Programming Language :: Python
Classifier: Programming Language :: Python :: 3
Classifier: Programming Language :: Python :: 3 :: Only
Classifier: Programming Language :: Python :: 3.8
Classifier: Programming Language :: Python :: 3.9
Requires-Python: >=3.8
License-File: LICENSE/LICENSE
Requires-Dist: matplotlib (>=3.3)
Provides-Extra: docs
Requires-Dist: Sphinx (>=1.5) ; extra == 'docs'
Requires-Dist: furo ; extra == 'docs'
Requires-Dist: myst-nb ; extra == 'docs'
Requires-Dist: sphinx-copybutton ; extra == 'docs'
Requires-Dist: sphinx-gallery ; extra == 'docs'
